mcp_allthetools/__init__.py
mcp_allthetools/server.py
mcp_allthetools/tools.py
mseep_mcp_allthetools-0.1.4.dist-info/licenses/LICENSE
mseep_mcp_allthetools-0.1.4.dist-info/METADATA
mseep_mcp_allthetools-0.1.4.dist-info/WHEEL
mseep_mcp_allthetools-0.1.4.dist-info/entry_points.txt
mseep_mcp_allthetools-0.1.4.dist-info/top_level.txt
mseep_mcp_allthetools-0.1.4.dist-info/RECORD
